LICENSE
MANIFEST.in
README.rst
dev-requirements.txt
requirements.txt
setup.cfg
setup.py
test-requirements.txt
docs/api.rst
docs/conf.py
docs/examples.rst
docs/history.rst
docs/index.rst
sprockets/__init__.py
sprockets.handlers.heartbeat.egg-info/PKG-INFO
sprockets.handlers.heartbeat.egg-info/SOURCES.txt
sprockets.handlers.heartbeat.egg-info/dependency_links.txt
sprockets.handlers.heartbeat.egg-info/namespace_packages.txt
sprockets.handlers.heartbeat.egg-info/not-zip-safe
sprockets.handlers.heartbeat.egg-info/requires.txt
sprockets.handlers.heartbeat.egg-info/top_level.txt
sprockets/handlers/__init__.py
sprockets/handlers/heartbeat/__init__.py