Metadata-Version: 1.1
Name: sprockets.handlers.heartbeat
Version: 0.1.0
Summary: A callback-based heartbeat handler
Home-page: https://github.com/sprockets/sprockets.handlers.heartbeat.git
Author: AWeber Communications
Author-email: api@aweber.com
License: Copyright (c) 2014 AWeber Communications
